xmitgcm/__init__.py
xmitgcm/_version.py
xmitgcm/default_diagnostics.py
xmitgcm/file_utils.py
xmitgcm/mds_store.py
xmitgcm/utils.py
xmitgcm/variables.py
xmitgcm/llcreader/__init__.py
xmitgcm/llcreader/duck_array_ops.py
xmitgcm/llcreader/known_models.py
xmitgcm/llcreader/llcmodel.py
xmitgcm/llcreader/llcutils.py
xmitgcm/llcreader/shrunk_index.py
xmitgcm/llcreader/stores.py
xmitgcm/test/__init__.py
xmitgcm/test/test_file_utils.py
xmitgcm/test/test_llcreader.py
xmitgcm/test/test_mds_store.py
xmitgcm/test/test_utils.py
xmitgcm/test/test_xmitgcm_common.py
xmitgcm-0.5.2.dist-info/LICENSE
xmitgcm-0.5.2.dist-info/METADATA
xmitgcm-0.5.2.dist-info/WHEEL
xmitgcm-0.5.2.dist-info/top_level.txt
xmitgcm-0.5.2.dist-info/RECORD
