Metadata-Version: 1.2
Name: xmitgcm
Version: 0.5.2
Summary: Read MITgcm mds binary files into xarray
Home-page: https://github.com/MITgcm/xmitgcm
Author: Ryan Abernathey
Author-email: rpa@ldeo.columbia.edu
License: Apache
Platform: UNKNOWN
Classifier: Development Status :: 4 - Beta
Classifier: License :: OSI Approved :: Apache Software License
Classifier: Operating System :: OS Independent
Classifier: Intended Audience :: Science/Research
Classifier: Programming Language :: Python
Classifier: Programming Language :: Python :: 3
Classifier: Programming Language :: Python :: 3.7
Classifier: Programming Language :: Python :: 3.8
Classifier: Programming Language :: Python :: 3.9
Classifier: Topic :: Scientific/Engineering
Requires-Python: >=3.7
